{"id":"ml-auto-feature","label":"自动特征工程","description":"自动生成数值交叉、比率、日期和文本长度特征","category":"ML · 特征工程","kind":"generic","properties":[{"name":"includeCross","label":"交叉特征","type":"boolean","default":true},{"name":"maxFeatures","label":"最大新增特征","type":"number","default":30,"min":1,"max":200}],"ports":[{"name":"data","label":"数据","type":"json-rows","direction":"input","required":true},{"name":"data","label":"增强数据","type":"json-rows","direction":"output"},{"name":"features","label":"特征列表","type":"array","direction":"output"}],"keywords":["自动特征","交叉特征","feature engineering"]}
