{
  "id": "example_check_valve_selection_form_edit",
  "name": "数据修改",
  "formMode": "lookup-edit",
  "viewport": {
    "zoom": 1,
    "panX": 0,
    "panY": 0
  },
  "gridSize": 10,
  "createdAt": "2026-07-06T18:00:00.000Z",
  "updatedAt": "2026-07-06T18:00:00.000Z",
  "bindings": [],
  "components": [
    {
      "id": "example_check_valve_selection_edit_title",
      "type": "text",
      "x": 24,
      "y": 24,
      "width": 760,
      "height": 40,
      "zIndex": 1,
      "props": {
        "name": "example_check_valve_selection_edit_title",
        "content": "止回阀选型 · 数据修改",
        "fontSize": 22,
        "color": "#0f172a",
        "fontWeight": "bold"
      }
    },
    {
      "id": "example_check_valve_selection_edit_hint",
      "type": "text",
      "x": 24,
      "y": 70,
      "width": 760,
      "height": 28,
      "zIndex": 1,
      "fieldBinding": "处理提示",
      "props": {
        "name": "example_check_valve_selection_edit_hint",
        "content": "处理提示",
        "fontSize": 13,
        "color": "#475569"
      }
    },
    {
      "id": "example_check_valve_selection_search_filter",
      "type": "select",
      "x": 24,
      "y": 116,
      "width": 220,
      "height": 60,
      "zIndex": 2,
      "fieldBinding": "筛选状态",
      "props": {
        "name": "筛选状态",
        "label": "筛选状态",
        "options": [
          "全部",
          "待选型",
          "待复核",
          "已通过"
        ],
        "defaultValue": "全部"
      }
    },
    {
      "id": "example_check_valve_selection_search_btn",
      "type": "button",
      "x": 264,
      "y": 116,
      "width": 180,
      "height": 50,
      "zIndex": 3,
      "props": {
        "name": "example_check_valve_selection_search_btn",
        "label": "查询记录",
        "variant": "primary",
        "events": {
          "onClick": "const filterValue = String(ctx.getValue('筛选状态') || '全部');\nconst rows = ctx.querySheet('valve_requests').filter((row) => filterValue === '全部' || String(row?.选型状态 ?? '') === filterValue);\nawait ctx.setValue('example_check_valve_selection_列表', rows);\nawait ctx.setValue('处理提示', `已加载 ${rows.length} 条记录`);"
        }
      }
    },
    {
      "id": "example_check_valve_selection_result_table",
      "type": "table",
      "x": 24,
      "y": 196,
      "width": 520,
      "height": 260,
      "zIndex": 2,
      "fieldBinding": "example_check_valve_selection_列表",
      "props": {
        "name": "example_check_valve_selection_列表",
        "columns": [
          "申请单号",
          "项目名称",
          "介质",
          "公称通径DN",
          "压力等级PN",
          "推荐型号",
          "选型状态"
        ],
        "rows": 5,
        "events": {
          "onRowClick": "const row = ctx.detail?.row || {};\nawait ctx.setValue('申请单号', row.申请单号 ?? '');\nawait ctx.setValue('项目名称', row.项目名称 ?? '');\nawait ctx.setValue('介质', row.介质 ?? '');\nawait ctx.setValue('公称通径DN', row.公称通径DN ?? '');\nawait ctx.setValue('压力等级PN', row.压力等级PN ?? '');\nawait ctx.setValue('设计温度', row.设计温度 ?? '');\nawait ctx.setValue('设计流量', row.设计流量 ?? '');\nawait ctx.setValue('推荐型号', row.推荐型号 ?? '');\nawait ctx.setValue('选型状态', row.选型状态 ?? '');\nawait ctx.setValue('原始申请单号', row.申请单号 ?? '');\nawait ctx.setValue('原始项目名称', row.项目名称 ?? '');\nawait ctx.setValue('原始介质', row.介质 ?? '');\nawait ctx.setValue('原始公称通径DN', row.公称通径DN ?? '');\nawait ctx.setValue('原始压力等级PN', row.压力等级PN ?? '');\nawait ctx.setValue('原始设计温度', row.设计温度 ?? '');\nawait ctx.setValue('原始设计流量', row.设计流量 ?? '');\nawait ctx.setValue('原始推荐型号', row.推荐型号 ?? '');\nawait ctx.setValue('原始选型状态', row.选型状态 ?? '');\nawait ctx.setValue('处理提示', `已载入 申请单号：${row.申请单号 || ''}`);"
        }
      }
    },
    {
      "id": "example_check_valve_selection_edit_0",
      "type": "number",
      "x": 568,
      "y": 196,
      "width": 200,
      "height": 60,
      "zIndex": 2,
      "fieldBinding": "申请单号",
      "props": {
        "name": "申请单号",
        "label": "申请单号",
        "required": false,
        "readonly": true,
        "placeholder": ""
      }
    },
    {
      "id": "example_check_valve_selection_edit_1",
      "type": "input",
      "x": 788,
      "y": 196,
      "width": 200,
      "height": 60,
      "zIndex": 2,
      "fieldBinding": "项目名称",
      "props": {
        "name": "项目名称",
        "label": "项目名称",
        "required": true,
        "readonly": false,
        "placeholder": "请输入项目名称"
      }
    },
    {
      "id": "example_check_valve_selection_edit_2",
      "type": "select",
      "x": 568,
      "y": 276,
      "width": 200,
      "height": 60,
      "zIndex": 2,
      "fieldBinding": "介质",
      "props": {
        "name": "介质",
        "label": "介质",
        "required": true,
        "readonly": false,
        "placeholder": "",
        "options": [
          "清水",
          "蒸汽",
          "油品",
          "腐蚀液"
        ]
      }
    },
    {
      "id": "example_check_valve_selection_edit_3",
      "type": "number",
      "x": 788,
      "y": 276,
      "width": 200,
      "height": 60,
      "zIndex": 2,
      "fieldBinding": "公称通径DN",
      "props": {
        "name": "公称通径DN",
        "label": "公称通径DN",
        "required": true,
        "readonly": false,
        "placeholder": ""
      }
    },
    {
      "id": "example_check_valve_selection_edit_4",
      "type": "number",
      "x": 568,
      "y": 356,
      "width": 200,
      "height": 60,
      "zIndex": 2,
      "fieldBinding": "压力等级PN",
      "props": {
        "name": "压力等级PN",
        "label": "压力等级PN",
        "required": true,
        "readonly": false,
        "placeholder": ""
      }
    },
    {
      "id": "example_check_valve_selection_edit_5",
      "type": "number",
      "x": 788,
      "y": 356,
      "width": 200,
      "height": 60,
      "zIndex": 2,
      "fieldBinding": "设计温度",
      "props": {
        "name": "设计温度",
        "label": "设计温度",
        "required": true,
        "readonly": false,
        "placeholder": ""
      }
    },
    {
      "id": "example_check_valve_selection_edit_6",
      "type": "number",
      "x": 568,
      "y": 436,
      "width": 200,
      "height": 60,
      "zIndex": 2,
      "fieldBinding": "设计流量",
      "props": {
        "name": "设计流量",
        "label": "设计流量",
        "required": true,
        "readonly": false,
        "placeholder": ""
      }
    },
    {
      "id": "example_check_valve_selection_edit_7",
      "type": "input",
      "x": 788,
      "y": 436,
      "width": 200,
      "height": 60,
      "zIndex": 2,
      "fieldBinding": "推荐型号",
      "props": {
        "name": "推荐型号",
        "label": "推荐型号",
        "required": false,
        "readonly": false,
        "placeholder": ""
      }
    },
    {
      "id": "example_check_valve_selection_edit_8",
      "type": "select",
      "x": 568,
      "y": 516,
      "width": 200,
      "height": 60,
      "zIndex": 2,
      "fieldBinding": "选型状态",
      "props": {
        "name": "选型状态",
        "label": "选型状态",
        "required": false,
        "readonly": false,
        "placeholder": "",
        "options": [
          "待选型",
          "待复核",
          "已通过"
        ]
      }
    },
    {
      "id": "example_check_valve_selection_update_btn",
      "type": "button",
      "x": 568,
      "y": 648,
      "width": 220,
      "height": 50,
      "zIndex": 3,
      "props": {
        "name": "example_check_valve_selection_update_btn",
        "label": "保存修改",
        "variant": "primary",
        "events": {
          "onClick": "const id = ctx.getValue('申请单号');\nif (!id && id !== 0) return ctx.showMessage('请先从左侧表格选择记录', 'error');\nconst medium = String(ctx.getValue('介质') || '');\nconst dn = Number(ctx.getValue('公称通径DN') || 0);\nconst pn = Number(ctx.getValue('压力等级PN') || 0);\nconst temp = Number(ctx.getValue('设计温度') || 0);\nlet model = 'H44H-16C';\nif (medium === '蒸汽') model = 'H41H-25P';\nelse if (medium === '腐蚀液') model = 'HC41F-16P';\nelse if (medium === '油品') model = 'H41H-25C';\nawait ctx.setValue('推荐型号', `${model}-DN${dn}`);\nawait ctx.setValue('选型状态', temp > 180 || pn >= 25 ? '待复核' : '已通过');\nawait ctx.runConfiguredWorkflow();\nawait ctx.setValue('处理提示', `止回阀选型已更新：${id}`);\nawait ctx.showMessage(`止回阀选型已更新：${id}`, 'success');"
        },
        "flowTriggers": {
          "onClick": {
            "enabled": true,
            "workflowId": "example_check_valve_selection_wf_update",
            "parameterMap": {
              "submit.formData": {
                "申请单号": "$form.申请单号",
                "项目名称": "$form.项目名称",
                "介质": "$form.介质",
                "公称通径DN": "$form.公称通径DN",
                "压力等级PN": "$form.压力等级PN",
                "设计温度": "$form.设计温度",
                "设计流量": "$form.设计流量",
                "推荐型号": "$form.推荐型号",
                "选型状态": "$form.选型状态"
              },
              "submit.originalData": {
                "申请单号": "$form.原始申请单号",
                "项目名称": "$form.原始项目名称",
                "介质": "$form.原始介质",
                "公称通径DN": "$form.原始公称通径DN",
                "压力等级PN": "$form.原始压力等级PN",
                "设计温度": "$form.原始设计温度",
                "设计流量": "$form.原始设计流量",
                "推荐型号": "$form.原始推荐型号",
                "选型状态": "$form.原始选型状态"
              }
            }
          }
        }
      }
    }
  ]
}
